drillholes/__init__.py
drillholes/dipconversion.py
drillholes/drillhole.py
drillholes/geodata.py
drillholes-0.0.2.dist-info/licenses/LICENSE
examples/carley_bore.py
examples/tampia.py
drillholes-0.0.2.dist-info/METADATA
drillholes-0.0.2.dist-info/WHEEL
drillholes-0.0.2.dist-info/top_level.txt
drillholes-0.0.2.dist-info/RECORD
