Metadata-Version: 2.4
Name: drillholes
Version: 0.0.2
Summary: Desurvey Compositing, Visualisation of drillholes from collar, assay and survey files
License-File: LICENSE
Requires-Dist: pandas
Requires-Dist: numpy
Requires-Dist: wellpathpy
Requires-Dist: tqdm
Requires-Dist: dhcomp
Requires-Dist: pyvista
Provides-Extra: dev
Requires-Dist: black; extra == "dev"
Requires-Dist: coverage; extra == "dev"
Dynamic: license-file
